src/claude.py
src/context.py
src/geneius.py
geneius-1.4.dist-info/LICENSE
geneius-1.4.dist-info/METADATA
geneius-1.4.dist-info/WHEEL
geneius-1.4.dist-info/entry_points.txt
geneius-1.4.dist-info/top_level.txt
geneius-1.4.dist-info/RECORD
