Metadata-Version: 2.1
Name: geneius
Version: 1.4
Summary: A tool for disease-gene evidence search and explanation
Home-page: https://github.com/aaronwtr/geneius
Author: Aaron Wenteler
License: MIT
License-File: LICENSE
Requires-Dist: anthropic
Requires-Dist: biopython
